biorepo_evaluator/__init__.py
biorepo_evaluator/all_corpuses.xlsx
biorepo_evaluator/my_functions.py
biorepo_evaluator-0.1.5.dist-info/METADATA
biorepo_evaluator-0.1.5.dist-info/WHEEL
biorepo_evaluator-0.1.5.dist-info/top_level.txt
biorepo_evaluator-0.1.5.dist-info/RECORD
