Metadata-Version: 2.1
Name: biorepo-evaluator
Version: 0.1.5
Summary: Library for automatic evaluation of repository
Home-page: UNKNOWN
Author: Shiva Aryal
License: UNKNOWN
Platform: UNKNOWN
